<?xml version="1.0" encoding="utf-8" standalone="yes" ?>
<T3locallang>
	<meta type="array">
		<type>database</type>
		<description>Language labels for database tables/fields belonging to extension 'ics_utopia'</description>
	</meta>
	<data type="array">
		<languageKey index="default" type="array">
			<label index="tx_icsutopia_site">Generated Site ID</label>
			<label index="tx_icsutopia_site.url">Site URL</label>
			<label index="tx_icsutopia_site.be_group">Backend group</label>
			<label index="tx_icsutopia_site.base_model">Base model</label>
			<label index="tx_icsutopia_site.title">Site title</label>
			<label index="tx_icsutopia_site.main_storage">Main storage page</label>
			<label index="tt_content.CType_pi1">Site creation</label>
		</languageKey>
		<languageKey index="fr" type="array">
			<label index="tx_icsutopia_site">Identifiant de site généré</label>
			<label index="tx_icsutopia_site.url">URL du site</label>
			<label index="tx_icsutopia_site.be_group">Groupe back-office</label>
			<label index="tx_icsutopia_site.base_model">Modèle de base</label>
			<label index="tx_icsutopia_site.title">Titre du site</label>
			<label index="tx_icsutopia_site.main_storage">Page de stockage principale</label>
			<label index="tt_content.CType_pi1">Création de site</label>
		</languageKey>
	</data>
</T3locallang>